{
  "Rob": {
    "top": 0,
    "jungle": 0,
    "mid": 0,
    "bot": 0,
    "support": 0
  },
  "Clom": {
    "top": 0,
    "jungle": 0,
    "mid": 0,
    "bot": 0,
    "support": 0
  },
  "Tien": {
    "top": 0,
    "jungle": 0,
    "mid": 0,
    "bot": 0,
    "support": 0
  },
  "Kasai": {
    "top": 0,
    "jungle": 0,
    "mid": 0,
    "bot": 0,
    "support": 0
  },
  "Jake": {
    "top": 0,
    "jungle": 0,
    "mid": 0,
    "bot": 0,
    "support": 0
  },
  "Xen Zenith": {
    "top": 0,
    "jungle": 0,
    "mid": 0,
    "bot": 0,
    "support": 0
  },
  "Krasith": {
    "top": 0,
    "jungle": 0,
    "mid": 0,
    "bot": 0,
    "support": 0
  },
  "Lamborjhini": {
    "top": 0,
    "jungle": 0,
    "mid": 0,
    "bot": 0,
    "support": 0
  },
  "Gwft": {
    "top": 0,
    "jungle": 0,
    "mid": 0,
    "bot": 0,
    "support": 0
  },
  "Bearcat": {
    "top": 0,
    "jungle": 0,
    "mid": 0,
    "bot": 0,
    "support": 0
  },
  "Azphra": {
    "top": 0,
    "jungle": 0,
    "mid": 0,
    "bot": 0,
    "support": 0
  }

}